ckan_rescue/__init__.py
ckan_rescue/__main__.py
ckan_rescue/cli.py
ckan_rescue/dcat.py
ckan_rescue-0.0.4.dist-info/licenses/LICENSE
ckan_rescue-0.0.4.dist-info/WHEEL
ckan_rescue-0.0.4.dist-info/entry_points.txt
ckan_rescue-0.0.4.dist-info/METADATA
ckan_rescue-0.0.4.dist-info/RECORD
