Metadata-Version: 2.4
Name: ckan-rescue
Version: 0.0.4
Summary: A tool to rescue (download) data from CKAN portals.
Author: Patricio Del Boca
Author-email: Patricio Del Boca <patriciodelboca@proton.me>
License-Expression: MIT
License-File: LICENSE
Requires-Python: >=3.10
Project-URL: Homepage, https://github.com/pdelboca/ckan-rescue
Project-URL: Issues, https://github.com/pdelboca/ckan-rescue/issues
